use_proper_hosting/__init__.py
use_proper_hosting-1.0.1.dist-info/LICENSE
use_proper_hosting-1.0.1.dist-info/METADATA
use_proper_hosting-1.0.1.dist-info/WHEEL
use_proper_hosting-1.0.1.dist-info/top_level.txt
use_proper_hosting-1.0.1.dist-info/RECORD
