Metadata-Version: 2.1
Name: use-proper-hosting
Version: 1.0.1
Summary: No more support server flooding with questions about unsupported hosting.
Home-page: https://github.com/playground1104/use-proper-hosting
Author: eunwoo1104
Author-email: sions04@naver.com
License: UNKNOWN
Platform: UNKNOWN
License-File: LICENSE
